pytextdist/__init__.py
pytextdist/edit_distance.py
pytextdist/input_validator.py
pytextdist/levenshtein.py
pytextdist/preprocessing.py
pytextdist/vector_similarity.py
pytextdist-0.1.6.dist-info/LICENSE
pytextdist-0.1.6.dist-info/METADATA
pytextdist-0.1.6.dist-info/WHEEL
pytextdist-0.1.6.dist-info/top_level.txt
pytextdist-0.1.6.dist-info/RECORD
